{
    "id": 2442696,
    "name": "Abteiweg",
    "staticId": "U29saW5nZW5kZWZhdWx0QWJ0ZWl3ZWc=",
    "hausNrList": [
        {
            "id": 2442697,
            "nr": "2",
            "plz": "",
            "staticId": "U29saW5nZW5BYnRlaXdlZzI="
        },
        {
            "id": 2442701,
            "nr": "2a",
            "plz": "",
            "staticId": "U29saW5nZW5BYnRlaXdlZzJh"
        },
        {
            "id": 2442704,
            "nr": "2b",
            "plz": "",
            "staticId": "U29saW5nZW5BYnRlaXdlZzJi"
        },
        {
            "id": 2442705,
            "nr": "2c",
            "plz": "",
            "staticId": "U29saW5nZW5BYnRlaXdlZzJj"
        },
        {
            "id": 2442706,
            "nr": "4",
            "plz": "",
            "staticId": "U29saW5nZW5BYnRlaXdlZzQ="
        },
        {
            "id": 2442707,
            "nr": "6",
            "plz": "",
            "staticId": "U29saW5nZW5BYnRlaXdlZzY="
        },
        {
            "id": 2442708,
            "nr": "6a",
            "plz": "",
            "staticId": "U29saW5nZW5BYnRlaXdlZzZh"
        },
        {
            "id": 2442709,
            "nr": "8",
            "plz": "",
            "staticId": "U29saW5nZW5BYnRlaXdlZzg="
        },
        {
            "id": 2442710,
            "nr": "10",
            "plz": "",
            "staticId": "U29saW5nZW5BYnRlaXdlZzEw"
        },
        {
            "id": 2442711,
            "nr": "10a",
            "plz": "",
            "staticId": "U29saW5nZW5BYnRlaXdlZzEwYQ=="
        },
        {
            "id": 2442712,
            "nr": "10b",
            "plz": "",
            "staticId": "U29saW5nZW5BYnRlaXdlZzEwYg=="
        },
        {
            "id": 2442713,
            "nr": "12",
            "plz": "",
            "staticId": "U29saW5nZW5BYnRlaXdlZzEy"
        },
        {
            "id": 2442714,
            "nr": "13",
            "plz": "",
            "staticId": "U29saW5nZW5BYnRlaXdlZzEz"
        },
        {
            "id": 2442715,
            "nr": "15",
            "plz": "",
            "staticId": "U29saW5nZW5BYnRlaXdlZzE1"
        },
        {
            "id": 2442716,
            "nr": "17",
            "plz": "",
            "staticId": "U29saW5nZW5BYnRlaXdlZzE3"
        },
        {
            "id": 2442717,
            "nr": "18",
            "plz": "",
            "staticId": "U29saW5nZW5BYnRlaXdlZzE4"
        },
        {
            "id": 2442718,
            "nr": "19",
            "plz": "",
            "staticId": "U29saW5nZW5BYnRlaXdlZzE5"
        },
        {
            "id": 2442719,
            "nr": "20",
            "plz": "",
            "staticId": "U29saW5nZW5BYnRlaXdlZzIw"
        },
        {
            "id": 2442720,
            "nr": "21",
            "plz": "",
            "staticId": "U29saW5nZW5BYnRlaXdlZzIx"
        },
        {
            "id": 2442721,
            "nr": "22",
            "plz": "",
            "staticId": "U29saW5nZW5BYnRlaXdlZzIy"
        },
        {
            "id": 2442722,
            "nr": "23",
            "plz": "",
            "staticId": "U29saW5nZW5BYnRlaXdlZzIz"
        },
        {
            "id": 2442723,
            "nr": "24",
            "plz": "",
            "staticId": "U29saW5nZW5BYnRlaXdlZzI0"
        },
        {
            "id": 2442724,
            "nr": "25",
            "plz": "",
            "staticId": "U29saW5nZW5BYnRlaXdlZzI1"
        },
        {
            "id": 2442725,
            "nr": "26",
            "plz": "",
            "staticId": "U29saW5nZW5BYnRlaXdlZzI2"
        },
        {
            "id": 2442726,
            "nr": "27",
            "plz": "",
            "staticId": "U29saW5nZW5BYnRlaXdlZzI3"
        },
        {
            "id": 2442727,
            "nr": "29",
            "plz": "",
            "staticId": "U29saW5nZW5BYnRlaXdlZzI5"
        },
        {
            "id": 2442728,
            "nr": "31",
            "plz": "",
            "staticId": "U29saW5nZW5BYnRlaXdlZzMx"
        },
        {
            "id": 2442729,
            "nr": "32",
            "plz": "",
            "staticId": "U29saW5nZW5BYnRlaXdlZzMy"
        },
        {
            "id": 2442730,
            "nr": "33",
            "plz": "",
            "staticId": "U29saW5nZW5BYnRlaXdlZzMz"
        },
        {
            "id": 2442731,
            "nr": "34",
            "plz": "",
            "staticId": "U29saW5nZW5BYnRlaXdlZzM0"
        },
        {
            "id": 2442732,
            "nr": "35",
            "plz": "",
            "staticId": "U29saW5nZW5BYnRlaXdlZzM1"
        },
        {
            "id": 2442733,
            "nr": "36",
            "plz": "",
            "staticId": "U29saW5nZW5BYnRlaXdlZzM2"
        },
        {
            "id": 2442734,
            "nr": "37",
            "plz": "",
            "staticId": "U29saW5nZW5BYnRlaXdlZzM3"
        },
        {
            "id": 2442735,
            "nr": "38",
            "plz": "",
            "staticId": "U29saW5nZW5BYnRlaXdlZzM4"
        },
        {
            "id": 2442736,
            "nr": "39",
            "plz": "",
            "staticId": "U29saW5nZW5BYnRlaXdlZzM5"
        },
        {
            "id": 2442737,
            "nr": "40",
            "plz": "",
            "staticId": "U29saW5nZW5BYnRlaXdlZzQw"
        },
        {
            "id": 2442738,
            "nr": "41",
            "plz": "",
            "staticId": "U29saW5nZW5BYnRlaXdlZzQx"
        },
        {
            "id": 2442739,
            "nr": "43",
            "plz": "",
            "staticId": "U29saW5nZW5BYnRlaXdlZzQz"
        },
        {
            "id": 2442740,
            "nr": "45",
            "plz": "",
            "staticId": "U29saW5nZW5BYnRlaXdlZzQ1"
        },
        {
            "id": 2442741,
            "nr": "47",
            "plz": "",
            "staticId": "U29saW5nZW5BYnRlaXdlZzQ3"
        },
        {
            "id": 2442742,
            "nr": "49",
            "plz": "",
            "staticId": "U29saW5nZW5BYnRlaXdlZzQ5"
        },
        {
            "id": 2442743,
            "nr": "50",
            "plz": "",
            "staticId": "U29saW5nZW5BYnRlaXdlZzUw"
        },
        {
            "id": 2442744,
            "nr": "51",
            "plz": "",
            "staticId": "U29saW5nZW5BYnRlaXdlZzUx"
        },
        {
            "id": 2442745,
            "nr": "52",
            "plz": "",
            "staticId": "U29saW5nZW5BYnRlaXdlZzUy"
        },
        {
            "id": 2442746,
            "nr": "53",
            "plz": "",
            "staticId": "U29saW5nZW5BYnRlaXdlZzUz"
        },
        {
            "id": 2442747,
            "nr": "54",
            "plz": "",
            "staticId": "U29saW5nZW5BYnRlaXdlZzU0"
        },
        {
            "id": 2442748,
            "nr": "55",
            "plz": "",
            "staticId": "U29saW5nZW5BYnRlaXdlZzU1"
        },
        {
            "id": 2442749,
            "nr": "56",
            "plz": "",
            "staticId": "U29saW5nZW5BYnRlaXdlZzU2"
        },
        {
            "id": 2442750,
            "nr": "57",
            "plz": "",
            "staticId": "U29saW5nZW5BYnRlaXdlZzU3"
        },
        {
            "id": 2442751,
            "nr": "59",
            "plz": "",
            "staticId": "U29saW5nZW5BYnRlaXdlZzU5"
        },
        {
            "id": 2442752,
            "nr": "61",
            "plz": "",
            "staticId": "U29saW5nZW5BYnRlaXdlZzYx"
        },
        {
            "id": 2442753,
            "nr": "63",
            "plz": "",
            "staticId": "U29saW5nZW5BYnRlaXdlZzYz"
        },
        {
            "id": 2442754,
            "nr": "64",
            "plz": "",
            "staticId": "U29saW5nZW5BYnRlaXdlZzY0"
        },
        {
            "id": 2442755,
            "nr": "65",
            "plz": "",
            "staticId": "U29saW5nZW5BYnRlaXdlZzY1"
        },
        {
            "id": 2442756,
            "nr": "67",
            "plz": "",
            "staticId": "U29saW5nZW5BYnRlaXdlZzY3"
        },
        {
            "id": 2442757,
            "nr": "69",
            "plz": "",
            "staticId": "U29saW5nZW5BYnRlaXdlZzY5"
        },
        {
            "id": 2442758,
            "nr": "71",
            "plz": "",
            "staticId": "U29saW5nZW5BYnRlaXdlZzcx"
        },
        {
            "id": 2442759,
            "nr": "74",
            "plz": "",
            "staticId": "U29saW5nZW5BYnRlaXdlZzc0"
        },
        {
            "id": 2442760,
            "nr": "87",
            "plz": "",
            "staticId": "U29saW5nZW5BYnRlaXdlZzg3"
        },
        {
            "id": 2442761,
            "nr": "89",
            "plz": "",
            "staticId": "U29saW5nZW5BYnRlaXdlZzg5"
        },
        {
            "id": 2442762,
            "nr": "91",
            "plz": "",
            "staticId": "U29saW5nZW5BYnRlaXdlZzkx"
        },
        {
            "id": 2442763,
            "nr": "93",
            "plz": "",
            "staticId": "U29saW5nZW5BYnRlaXdlZzkz"
        },
        {
            "id": 2442764,
            "nr": "95",
            "plz": "",
            "staticId": "U29saW5nZW5BYnRlaXdlZzk1"
        },
        {
            "id": 2442765,
            "nr": "97",
            "plz": "",
            "staticId": "U29saW5nZW5BYnRlaXdlZzk3"
        },
        {
            "id": 2442766,
            "nr": "99",
            "plz": "",
            "staticId": "U29saW5nZW5BYnRlaXdlZzk5"
        },
        {
            "id": 2442767,
            "nr": "101",
            "plz": "",
            "staticId": "U29saW5nZW5BYnRlaXdlZzEwMQ=="
        },
        {
            "id": 2442768,
            "nr": "103",
            "plz": "",
            "staticId": "U29saW5nZW5BYnRlaXdlZzEwMw=="
        },
        {
            "id": 2442769,
            "nr": "105",
            "plz": "",
            "staticId": "U29saW5nZW5BYnRlaXdlZzEwNQ=="
        },
        {
            "id": 2442770,
            "nr": "107",
            "plz": "",
            "staticId": "U29saW5nZW5BYnRlaXdlZzEwNw=="
        },
        {
            "id": 2442771,
            "nr": "109",
            "plz": "",
            "staticId": "U29saW5nZW5BYnRlaXdlZzEwOQ=="
        },
        {
            "id": 2442772,
            "nr": "111",
            "plz": "",
            "staticId": "U29saW5nZW5BYnRlaXdlZzExMQ=="
        },
        {
            "id": 2442773,
            "nr": "113",
            "plz": "",
            "staticId": "U29saW5nZW5BYnRlaXdlZzExMw=="
        },
        {
            "id": 2442774,
            "nr": "115",
            "plz": "",
            "staticId": "U29saW5nZW5BYnRlaXdlZzExNQ=="
        },
        {
            "id": 2442775,
            "nr": "117",
            "plz": "",
            "staticId": "U29saW5nZW5BYnRlaXdlZzExNw=="
        },
        {
            "id": 2442776,
            "nr": "119",
            "plz": "",
            "staticId": "U29saW5nZW5BYnRlaXdlZzExOQ=="
        },
        {
            "id": 2442777,
            "nr": "121",
            "plz": "",
            "staticId": "U29saW5nZW5BYnRlaXdlZzEyMQ=="
        },
        {
            "id": 2442778,
            "nr": "123",
            "plz": "",
            "staticId": "U29saW5nZW5BYnRlaXdlZzEyMw=="
        },
        {
            "id": 2442779,
            "nr": "125",
            "plz": "",
            "staticId": "U29saW5nZW5BYnRlaXdlZzEyNQ=="
        },
        {
            "id": 2442780,
            "nr": "127",
            "plz": "",
            "staticId": "U29saW5nZW5BYnRlaXdlZzEyNw=="
        },
        {
            "id": 2442781,
            "nr": "129",
            "plz": "",
            "staticId": "U29saW5nZW5BYnRlaXdlZzEyOQ=="
        },
        {
            "id": 2442782,
            "nr": "131",
            "plz": "",
            "staticId": "U29saW5nZW5BYnRlaXdlZzEzMQ=="
        },
        {
            "id": 2442783,
            "nr": "133",
            "plz": "",
            "staticId": "U29saW5nZW5BYnRlaXdlZzEzMw=="
        },
        {
            "id": 2442784,
            "nr": "135",
            "plz": "",
            "staticId": "U29saW5nZW5BYnRlaXdlZzEzNQ=="
        },
        {
            "id": 2442785,
            "nr": "137",
            "plz": "",
            "staticId": "U29saW5nZW5BYnRlaXdlZzEzNw=="
        },
        {
            "id": 2442786,
            "nr": "139",
            "plz": "",
            "staticId": "U29saW5nZW5BYnRlaXdlZzEzOQ=="
        },
        {
            "id": 2442787,
            "nr": "141",
            "plz": "",
            "staticId": "U29saW5nZW5BYnRlaXdlZzE0MQ=="
        },
        {
            "id": 2442788,
            "nr": "143",
            "plz": "",
            "staticId": "U29saW5nZW5BYnRlaXdlZzE0Mw=="
        }
    ],
    "plz": null,
    "ort": {
        "id": 2442650,
        "name": "Solingen"
    },
    "ortsteilName": "default"
}